pns_ai/__init__.py
pns_ai/py.typed
pnslab_ai_sdk-1.0.0.dist-info/licenses/LICENSE
pnslab_ai_sdk-1.0.0.dist-info/METADATA
pnslab_ai_sdk-1.0.0.dist-info/WHEEL
pnslab_ai_sdk-1.0.0.dist-info/top_level.txt
pnslab_ai_sdk-1.0.0.dist-info/RECORD
