Metadata-Version: 2.4
Name: pnslab-ai-sdk
Version: 1.0.0
Summary: PNS AI Hub SDK - AI 서비스를 쉽게 사용할 수 있는 Python SDK
Author-email: PNS Lab <dev@pns-lab.com>
Maintainer-email: PNS Lab <dev@pns-lab.com>
License: MIT
Project-URL: Homepage, https://ai.pns-lab.com
Project-URL: Documentation, https://ai.pns-lab.com/sdk
Project-URL: Repository, https://github.com/pns-lab/ai-sdk
Project-URL: Issues, https://github.com/pns-lab/ai-sdk/issues
Keywords: ai,pns-lab,bedrock,claude,sdk,chatbot,nlp
Classifier: Development Status :: 4 - Beta
Classifier: Intended Audience :: Developers
Classifier: License :: OSI Approved :: MIT License
Classifier: Operating System :: OS Independent
Classifier: Programming Language :: Python :: 3
Classifier: Programming Language :: Python :: 3.8
Classifier: Programming Language :: Python :: 3.9
Classifier: Programming Language :: Python :: 3.10
Classifier: Programming Language :: Python :: 3.11
Classifier: Programming Language :: Python :: 3.12
Classifier: Topic :: Scientific/Engineering :: Artificial Intelligence
Requires-Python: >=3.8
License-File: LICENSE
Requires-Dist: requests>=2.25.0
Requires-Dist: pycryptodome>=3.15.0
Provides-Extra: dev
Requires-Dist: pytest>=7.0.0; extra == "dev"
Requires-Dist: pytest-asyncio>=0.21.0; extra == "dev"
Dynamic: license-file
